pyprobyto/__init__.py
pyprobyto/mlmonitor.py
pyprobyto-0.1.2.dist-info/METADATA
pyprobyto-0.1.2.dist-info/WHEEL
pyprobyto-0.1.2.dist-info/top_level.txt
pyprobyto-0.1.2.dist-info/RECORD
